onepass_env/__init__.py
onepass_env/api.py
onepass_env-0.0.1a0.dist-info/LICENSE.txt
onepass_env-0.0.1a0.dist-info/METADATA
onepass_env-0.0.1a0.dist-info/WHEEL
onepass_env-0.0.1a0.dist-info/top_level.txt
onepass_env-0.0.1a0.dist-info/RECORD
