Metadata-Version: 2.1
Name: onepass_env
Version: 0.0.1a0
Summary: A simple package to populate env variables from 1Password
Home-page: https://github.com/rokn/onepass_env
Author: Antonio Mindov
Author-email: amindov98@gmail.com
License: MIT
Project-URL: Source, https://github.com/rokn/onepass_env
Platform: any
Classifier: Development Status :: 4 - Beta
Classifier: Programming Language :: Python
License-File: LICENSE.txt
Requires-Dist: python-dotenv
Requires-Dist: 1password
Provides-Extra: testing
Requires-Dist: setuptools ; extra == 'testing'
Requires-Dist: pytest ; extra == 'testing'
Requires-Dist: pytest-cov ; extra == 'testing'
